odoo10_addon_mail_digest-10.0.1.0.2-py2.7-nspkg.pth
odoo/addons/mail_digest/README.rst
odoo/addons/mail_digest/__init__.py
odoo/addons/mail_digest/__manifest__.py
odoo/addons/mail_digest/data/config_param.xml
odoo/addons/mail_digest/data/ir_cron.xml
odoo/addons/mail_digest/demo/ir_ui_view.xml
odoo/addons/mail_digest/demo/mail_template.xml
odoo/addons/mail_digest/i18n/am.po
odoo/addons/mail_digest/i18n/ar.po
odoo/addons/mail_digest/i18n/bg.po
odoo/addons/mail_digest/i18n/bs.po
odoo/addons/mail_digest/i18n/ca.po
odoo/addons/mail_digest/i18n/ca_ES.po
odoo/addons/mail_digest/i18n/cs.po
odoo/addons/mail_digest/i18n/da.po
odoo/addons/mail_digest/i18n/de.po
odoo/addons/mail_digest/i18n/el_GR.po
odoo/addons/mail_digest/i18n/en_GB.po
odoo/addons/mail_digest/i18n/es.po
odoo/addons/mail_digest/i18n/es_AR.po
odoo/addons/mail_digest/i18n/es_CL.po
odoo/addons/mail_digest/i18n/es_CO.po
odoo/addons/mail_digest/i18n/es_CR.po
odoo/addons/mail_digest/i18n/es_DO.po
odoo/addons/mail_digest/i18n/es_EC.po
odoo/addons/mail_digest/i18n/es_ES.po
odoo/addons/mail_digest/i18n/es_MX.po
odoo/addons/mail_digest/i18n/es_PE.po
odoo/addons/mail_digest/i18n/es_PY.po
odoo/addons/mail_digest/i18n/es_VE.po
odoo/addons/mail_digest/i18n/et.po
odoo/addons/mail_digest/i18n/eu.po
odoo/addons/mail_digest/i18n/fa.po
odoo/addons/mail_digest/i18n/fi.po
odoo/addons/mail_digest/i18n/fr.po
odoo/addons/mail_digest/i18n/fr_CA.po
odoo/addons/mail_digest/i18n/fr_CH.po
odoo/addons/mail_digest/i18n/gl.po
odoo/addons/mail_digest/i18n/gl_ES.po
odoo/addons/mail_digest/i18n/he.po
odoo/addons/mail_digest/i18n/hr.po
odoo/addons/mail_digest/i18n/hr_HR.po
odoo/addons/mail_digest/i18n/hu.po
odoo/addons/mail_digest/i18n/id.po
odoo/addons/mail_digest/i18n/it.po
odoo/addons/mail_digest/i18n/ja.po
odoo/addons/mail_digest/i18n/ko.po
odoo/addons/mail_digest/i18n/lt.po
odoo/addons/mail_digest/i18n/lt_LT.po
odoo/addons/mail_digest/i18n/lv.po
odoo/addons/mail_digest/i18n/mail_digest.pot
odoo10_addon_mail_digest-10.0.1.0.2.dist-info/DESCRIPTION.rst
odoo10_addon_mail_digest-10.0.1.0.2.dist-info/METADATA
odoo10_addon_mail_digest-10.0.1.0.2.dist-info/RECORD
odoo10_addon_mail_digest-10.0.1.0.2.dist-info/WHEEL
odoo10_addon_mail_digest-10.0.1.0.2.dist-info/metadata.json
odoo10_addon_mail_digest-10.0.1.0.2.dist-info/namespace_packages.txt
odoo10_addon_mail_digest-10.0.1.0.2.dist-info/top_level.txt
